{
  "HI": {
    "font-family": {
      "$type": "text",
      "$value": "Roboto"
    },
    "font-weight": {
      "Light": {
        "$type": "text",
        "$value": "Light"
      },
      "Regular": {
        "$type": "text",
        "$value": "Regular"
      },
      "Semi Bold": {
        "$type": "text",
        "$value": "SemiBold"
      },
      "Italic": {
        "$type": "text",
        "$value": "Italic"
      },
      "medium": {
        "$type": "text",
        "$value": "Medium"
      }
    }
  }
}